zkt/__init__.py
zkt/steps/__init__.py
zkt-1.0.3.dist-info/METADATA
zkt-1.0.3.dist-info/WHEEL
zkt-1.0.3.dist-info/top_level.txt
zkt-1.0.3.dist-info/RECORD
