Metadata-Version: 2.1
Name: zkt
Version: 1.0.3
Summary: Helper tool for api test automation
Home-page: UNKNOWN
Author: Noé Cruz
Author-email: contactozurckz@gmail.com
License: MIT
Keywords: zurckz test testing
Platform: UNKNOWN
Requires-Python: >=3.6
Requires-Dist: zpy-api-core
